{
  "battleshit": [
    {
      "namn": "Bert A.",
      "kommentar": "haha bajs",
      "betyg": 3
    },
    {
      "namn": "Jens Jon J.",
      "kommentar": "Superkladdigt, rent ut sagt vidrigt spel.",
      "betyg": 1
    }
  ],
  "sten-sax-pase": [
    {
      "namn": "Ing-marie U.",
      "kommentar": "Påsen gick sönder efter första matchen. 2/5",
      "betyg": 2
    },
    {
      "namn": "Britt B.",
      "kommentar": "Utöver ett roligt spel så kan stenen användas som prydnad :)",
      "betyg": 4
    },
    {
      "namn": "Emily",
      "kommentar": "Good but I was missing the well. Will have to buy that somewhere else.",
      "betyg": 2
    }
  ],
  "med-samma-ord": [
    {
      "namn": "Sven Q.",
      "kommentar": "Va jätte hypad och tog med det till en hemmafest men alla tröttnade ganska snabbt.",
      "betyg": 1
    },
    {
      "namn": "Lina 6 år",
      "kommentar": "Superbra lära sig svenska.",
      "betyg": 1
    }
  ],
  "cheese-board": [
    {
      "namn": "Sven Q.",
      "kommentar": "Gillar inte ädelost. Har ni en variant med brie?",
      "betyg": 1
    },
    {
      "namn": "Alex",
      "kommentar": "Superkul och gott, men tråkigt att man bara får spela en gång. Sen blir det väldigt orättvist liksom. Önskar det fanns marmelad till. Brädet skulle kunna vara av kex?",
      "betyg": 4
    }
  ],
  "gelerattfallan": [
    {
      "namn": "Bert A.",
      "kommentar": "haha kladd",
      "betyg": 3
    }
  ],
  "cheesers": [
    {
      "namn": "Namn",
      "kommentar": "Vet inte varför jag köpte denna, jag är laktosintolerant.",
      "betyg": 3
    }
  ],
  "drakar och dank memes": [
    {
      "namn": "Örjan T.",
      "kommentar": "Körde detta med mitt barn barn. Det va ett märkligt spel... Men kul!",
      "betyg": 5
    },
    {
      "namn": "MemeKingen",
      "kommentar": "Bjuder på massor lolz :P",
      "betyg": 5
    }
  ], 
  "den-funna-diamanten": [
    {
      "namn": "Triss T.",
      "kommentar": "Köpte det men kom inte med några instruktioner....",
      "betyg": 1
    },
    {
      "namn": "Henrik O.",
      "kommentar": "Helt perfekt. Kan ba plocka fram från fickan när vi spelar och lura polarna att jag vann.",
      "betyg": 5
    }
  ],
  "agnej": [
    {
      "namn": "Sven-Erik Q.",
      "kommentar": "Jag är ingenjör och det här va nog det enklaste spelet jag spelat.",
      "betyg": 2
    },
    {
      "namn": "Anette",
      "kommentar": "Superkul att bygga. Bra replayability. Man kan ställa den på hyllan sen, blir en supersnygg inredningsdetalj. MVH Maritta",
      "betyg": 5
    }
  ],
  "tva-i-rad": [
    {
      "namn": "Tobias S.",
      "kommentar": "Älskar detta spel. Väldigt enkelt att lära sig, brukar köra mot min 3 åring. Han blir oftast väldigt arg när jag alltid verkar vinna.",
      "betyg": 5
    },
    {
      "namn": "Isak H.",
      "kommentar": "Förlorar hela tiden, sugit spel ngl",
      "betyg": 1
    },
    {
      "namn": "Tobias S.",
      "kommentar": "Riktigt stämningshöjare. Har alltid framme på party.",
      "betyg": 5
    }
  ],
  "fia utan knuff": [
    {
      "namn": "Rasmus R.",
      "kommentar": "Det här är ju en kopia på fia MED knuff. Men jag gillar det här spelets regler mer.",
      "betyg": 5
    },
    {
      "namn": "Dålig förlorare",
      "kommentar": "Så skönt att slippa förlora.",
      "betyg": 5
    }
  ],
  "hangman": [
    {
      "namn": "Lill-Erik",
      "kommentar": "Riktigt sjukt spel om man tänker efter. Gillart' hehe",
      "betyg": 1
    },
    {
      "namn": "Lill-Erik",
      "kommentar": "Oj, råkade lämna bara 1 stjärna i min andra review. Menade att ge 5.",
      "betyg": 5
    },
    {
      "namn": "Ronny Svensson",
      "kommentar": "Letat så länge efter det här!!! Fattar inte varför ingen annan säljer det. Så glad att jag lyckades köpa det.",
      "betyg": 3
    }
  ]
}
